guirpc/__init__.py
guirpc/manager.py
guirpc/amqp/__init__.py
guirpc/amqp/consumer.py
guirpc/amqp/decorators.py
guirpc/amqp/producer.py
guirpc/amqp/providers.py
guirpc/amqp/serializers.py
guirpc/amqp/utils.py
guirpc/amqp/domain/__init__.py
guirpc/amqp/domain/contracts.py
guirpc/amqp/domain/encoding.py
guirpc/amqp/domain/exceptions.py
guirpc/amqp/domain/mixins.py
guirpc/amqp/domain/objects.py
guirpc/commands/__init__.py
guirpc/commands/init.py
guirpc/commands/run.py
guirpc/fixtures/__init__.py
guirpc/fixtures/consumer/__init__.py
guirpc/fixtures/consumer/server.py
guirpc/fixtures/producer/__init__.py
guirpc/fixtures/producer/client.py
guirpc/resources/defaults.yaml
guirpc/resources/logging.yaml
guirpc-0.1.dist-info/METADATA
guirpc-0.1.dist-info/WHEEL
guirpc-0.1.dist-info/entry_points.txt
guirpc-0.1.dist-info/top_level.txt
guirpc-0.1.dist-info/RECORD
