Metadata-Version: 2.1
Name: guirpc
Version: 0.1
Summary: RPC core package to build a FaaS-like application service
Home-page: https://github.com/guiloga/guirpc
Author: Guillem López Garcia
Author-email: wyl.loga@gmail.com
License: MIT
Platform: UNKNOWN
Classifier: Development Status :: 1 - Planning
Classifier: Intended Audience :: Developers
Classifier: License :: OSI Approved :: MIT License
Classifier: Operating System :: OS Independent
Classifier: Programming Language :: Python :: 3
Classifier: Topic :: Software Development :: Libraries
Classifier: Topic :: Software Development :: Libraries :: Python Modules
Requires-Python: >=3.6
Requires-Dist: pika (==1.1.0)
Requires-Dist: click (==7.1.2)
Requires-Dist: PyYAML (==5.3.1)
Provides-Extra: dev
